leanhtml/__init__.py
leanhtml/leanhtml.py
leanhtml/templates/lean.html
leanhtml-0.1.dist-info/LICENSE
leanhtml-0.1.dist-info/METADATA
leanhtml-0.1.dist-info/WHEEL
leanhtml-0.1.dist-info/top_level.txt
leanhtml-0.1.dist-info/RECORD
